dbrider/__init__.py
dbrider/database.py
dbrider/decorator.py
dbrider/handler.py
dbrider/loader.py
dbrider/matcher.py
dbrider/model.py
dbrider-1.0.3.dist-info/METADATA
dbrider-1.0.3.dist-info/WHEEL
dbrider-1.0.3.dist-info/RECORD
